ethiopian_date/__init__.py
ethiopian_date/ethiopian_date.py
ethiopian_date/tests.py
ethiopian_date-1.0.dist-info/METADATA
ethiopian_date-1.0.dist-info/WHEEL
ethiopian_date-1.0.dist-info/top_level.txt
ethiopian_date-1.0.dist-info/RECORD
