Metadata-Version: 1.1
Name: ethiopian_date
Version: 1.0
Summary: Ethiopian date converter.
Home-page: http://github.com/rgaudin/tools
Author: UNKNOWN
Author-email: UNKNOWN
License: GNU General Public License (GPL), Version 3
Platform: UNKNOWN
Classifier: Development Status :: 4 - Beta
Classifier: Intended Audience :: Developers
Classifier: License :: OSI Approved :: GNU Library or Lesser General Public License (LGPL)
Classifier: Programming Language :: Python
Provides: ethiopian_date
